sssort-0.1.0.dist-info/METADATA
sssort-0.1.0.dist-info/WHEEL
sssort-0.1.0.dist-info/entry_points.txt
sssort-0.1.0.dist-info/licenses/LICENSE
sssort/__init__.py
sssort/functions.py
sssort/functions_post_processing.py
sssort/inspect_result.py
sssort/manual_merger.py
sssort/plotters.py
sssort/post_processing.py
sssort/run.py
sssort/setup.py
sssort/sssio.py
sssort/sssort.py
sssort-0.1.0.dist-info/RECORD
