Metadata-Version: 2.1
Name: SSSort
Version: 0.1.0
Summary: spike sorter for single sensillum recordings
Author-Email: Georg Raiser <grg2rsr@gmail.com>
License: MIT
Requires-Python: >=3.12
Requires-Dist: numpy>=1.24.2
Requires-Dist: scipy>=1.10.1
Requires-Dist: pandas>=1.5
Requires-Dist: matplotlib>=3.7
Requires-Dist: neo>=0.12.0
Requires-Dist: quantities>=0.14.1
Requires-Dist: elephant>=0.12.0
Requires-Dist: scikit-learn>=1.2.2
Requires-Dist: tqdm>=4.65.0
Requires-Dist: seaborn>=0.12
